rest_framework_jwk/__init__.py
rest_framework_jwk/admin.py
rest_framework_jwk/algorithms.py
rest_framework_jwk/apps.py
rest_framework_jwk/cache.py
rest_framework_jwk/exceptions.py
rest_framework_jwk/jwt.py
rest_framework_jwk/management/__init__.py
rest_framework_jwk/management/commands/__init__.py
rest_framework_jwk/management/commands/rotatejwk.py
rest_framework_jwk/migrations/0001_initial.py
rest_framework_jwk/migrations/__init__.py
rest_framework_jwk/models.py
rest_framework_jwk/settings.py
rest_framework_jwk/urls.py
rest_framework_jwk/utils.py
rest_framework_jwk/views.py
django_rest_framework_jwk-0.1.3.dist-info/LICENSE
django_rest_framework_jwk-0.1.3.dist-info/WHEEL
django_rest_framework_jwk-0.1.3.dist-info/METADATA
django_rest_framework_jwk-0.1.3.dist-info/RECORD
