Metadata-Version: 2.1
Name: django-rest-framework-jwk
Version: 0.1.3
Summary: Easy JSON Web Keys (JWK) for your Django project
License: MIT
Author: Gustavo Maronato
Author-email: gustavo@maronato.dev
Requires-Python: >=3.6,<4.0
Classifier: License :: OSI Approved :: MIT License
Classifier: Programming Language :: Python :: 3
Classifier: Programming Language :: Python :: 3.6
Classifier: Programming Language :: Python :: 3.7
Classifier: Programming Language :: Python :: 3.8
Classifier: Programming Language :: Python :: 3.9
Requires-Dist: Django
Requires-Dist: cryptography (>=3.3.1,<4.0.0)
Requires-Dist: djangorestframework (>=3.10,<4.0)
Requires-Dist: jwcrypto (>=0.8,<0.9)
